scansplitter/__init__.py
scansplitter/api.py
scansplitter/cli.py
scansplitter/detector.py
scansplitter/exif_handler.py
scansplitter/models.py
scansplitter/pdf_handler.py
scansplitter/processor.py
scansplitter/rotator.py
scansplitter/session.py
scansplitter/static/index.html
scansplitter/static/logo-rounded.png
scansplitter/static/logo.png
scansplitter/static/logo_grid_only.png
scansplitter/static/screenshot.png
scansplitter/static/vite.svg
scansplitter/static/assets/index-CAoUwdN0.css
scansplitter/static/assets/index-Dp8NQx_r.js
scansplitter-0.4.0.dist-info/licenses/LICENSE
scansplitter-0.4.0.dist-info/METADATA
scansplitter-0.4.0.dist-info/WHEEL
scansplitter-0.4.0.dist-info/entry_points.txt
scansplitter-0.4.0.dist-info/top_level.txt
scansplitter-0.4.0.dist-info/RECORD
