Metadata-Version: 2.4
Name: scansplitter
Version: 0.4.0
Summary: Automatically detect, split, and rotate multiple photos from scanned images
License-Expression: GPL-3.0-or-later
Project-URL: Homepage, https://github.com/madnex/scansplitter
Project-URL: Repository, https://github.com/madnex/scansplitter
Project-URL: Issues, https://github.com/madnex/scansplitter/issues
Keywords: scanner,photos,split,crop,rotate,opencv,image-processing
Classifier: Development Status :: 4 - Beta
Classifier: Environment :: Web Environment
Classifier: Framework :: FastAPI
Classifier: Intended Audience :: End Users/Desktop
Classifier: Operating System :: OS Independent
Classifier: Programming Language :: Python :: 3
Classifier: Programming Language :: Python :: 3.13
Classifier: Topic :: Multimedia :: Graphics :: Capture :: Scanners
Classifier: Topic :: Multimedia :: Graphics :: Graphics Conversion
Requires-Python: >=3.13
License-File: LICENSE
Requires-Dist: numpy>=2.4.0
Requires-Dist: opencv-python-headless>=4.11.0.86
Requires-Dist: pillow>=12.1.0
Requires-Dist: pymupdf>=1.26.7
Requires-Dist: fastapi>=0.115.0
Requires-Dist: uvicorn[standard]>=0.32.0
Requires-Dist: python-multipart>=0.0.9
Requires-Dist: piexif>=1.1.3
Requires-Dist: onnxruntime>=1.17.0
Dynamic: license-file
